feature_extraction/__init__.py
feature_extraction/object_detection/__init__.py
feature_extraction/object_detection/background_substraction.py
feature_extraction/object_detection/depth_estimation.py
feature_extraction/object_detection/detector.py
feature_extraction/segment_analysis/__init__.py
feature_extraction/segment_analysis/segment_anything.py
segcount/__init__.py
segcount/cconfig.py
segcount/demo.py
segcount/segment_and_count.py
segcount/feature_extraction/__init__.py
segcount/feature_extraction/object_detection/__init__.py
segcount/feature_extraction/object_detection/background_substraction.py
segcount/feature_extraction/object_detection/depth_estimation.py
segcount/feature_extraction/object_detection/detector.py
segcount/feature_extraction/segment_analysis/__init__.py
segcount/feature_extraction/segment_analysis/segment_anything.py
segcount/utils/__init__.py
segcount/utils/logger.py
segcount/utils/read_img.py
utils/__init__.py
utils/logger.py
utils/read_img.py
segcount-0.0.1.dist-info/METADATA
segcount-0.0.1.dist-info/WHEEL
segcount-0.0.1.dist-info/top_level.txt
segcount-0.0.1.dist-info/RECORD
