Metadata-Version: 2.1
Name: segcount
Version: 0.0.1
Summary: Segment and count object using SAM
Classifier: Programming Language :: Python :: 3
Classifier: Operating System :: OS Independent
Requires-Python: >=3.8
